pysenal/__init__.py
pysenal/io/__init__.py
pysenal/io/file.py
pysenal/utils/__init__.py
pysenal/utils/logger.py
pysenal/utils/utils.py
pysenal-0.1.4.dist-info/AUTHORS.rst
pysenal-0.1.4.dist-info/LICENSE.txt
pysenal-0.1.4.dist-info/METADATA
pysenal-0.1.4.dist-info/WHEEL
pysenal-0.1.4.dist-info/top_level.txt
pysenal-0.1.4.dist-info/RECORD
