Metadata-Version: 2.1
Name: pysenal
Version: 0.1.4
Summary: Python useful utilities methods, only for Python3
Home-page: https://github.com/supercoderhawk/pysenal
Author: xiayubin
Author-email: supercoderhawk@gmail.com
License: MIT
Classifier: Development Status :: 4 - Beta
Classifier: Programming Language :: Python
License-File: LICENSE.txt
License-File: AUTHORS.rst
